barfi/__init__.py
barfi/block_builder.py
barfi/compute_engine.py
barfi/option_builder.py
barfi/client/index.html
barfi/client/css/app.51aff32b.css
barfi/client/js/app.4b1442b7.js
barfi/client/js/app.4b1442b7.js.map
barfi/client/js/app.7f640bdf.js
barfi/client/js/app.7f640bdf.js.map
barfi/client/js/chunk-vendors.b25a8761.js
barfi/client/js/chunk-vendors.b25a8761.js.map
barfi/client/js/chunk-vendors.eb7fca41.js
barfi/client/js/chunk-vendors.eb7fca41.js.map
barfi/scheme/__init__.py
barfi/scheme/local_schema_manager.py
barfi/scheme/local_user_schema_manager.py
barfi/scheme/preset.py
barfi/scheme/schema_manager.py
tests/__init__.py
tests/debug.py
tests/demo.py
tests/test_app.py
tests/test_blocks.py
barfi_ext-0.8.1.1.dist-info/LICENSE
barfi_ext-0.8.1.1.dist-info/METADATA
barfi_ext-0.8.1.1.dist-info/WHEEL
barfi_ext-0.8.1.1.dist-info/top_level.txt
barfi_ext-0.8.1.1.dist-info/RECORD
